mpi4pyve/MPI.cpython-36m-x86_64-linux-gnu.so
mpi4pyve/MPI.pxd
mpi4pyve/__init__.pxd
mpi4pyve/__init__.py
mpi4pyve/__main__.py
mpi4pyve/bench.py
mpi4pyve/dl.cpython-36m-x86_64-linux-gnu.so
mpi4pyve/libmpi.pxd
mpi4pyve/mpi.cfg
mpi4pyve/run.py
mpi4pyve/futures/__init__.py
mpi4pyve/futures/__main__.py
mpi4pyve/futures/_base.py
mpi4pyve/futures/_lib.py
mpi4pyve/futures/aplus.py
mpi4pyve/futures/pool.py
mpi4pyve/futures/server.py
mpi4pyve/include/mpi4pyve/mpi.pxi
mpi4pyve/include/mpi4pyve/mpi4pyve.MPI.h
mpi4pyve/include/mpi4pyve/mpi4pyve.MPI_api.h
mpi4pyve/include/mpi4pyve/mpi4pyve.h
mpi4pyve/include/mpi4pyve/mpi4pyve.i
mpi4pyve/lib-pmpi/libmpe.so
mpi4pyve/lib-pmpi/libvt-hyb.so
mpi4pyve/lib-pmpi/libvt-mpi.so
mpi4pyve/lib-pmpi/libvt.so
mpi4pyve/util/__init__.py
mpi4pyve/util/nmpi_aveo_dma.py
mpi4pyve/veo/__init__.py
mpi4pyve/veo/veo.py
mpi4py_ve-1.0.1.post1.dist-info/LICENSE
mpi4py_ve-1.0.1.post1.dist-info/METADATA
mpi4py_ve-1.0.1.post1.dist-info/WHEEL
mpi4py_ve-1.0.1.post1.dist-info/top_level.txt
mpi4py_ve-1.0.1.post1.dist-info/RECORD
