Metadata-Version: 2.1
Name: mpi4py-ve
Version: 1.0.1.post1
Summary: Python bindings for MPI
Home-page: https://github.com/SX-Aurora/mpi4py-ve/
Author: NEC
Author-email: dev-nlcpy@sxarr.jp.nec.com
Maintainer: NEC
Maintainer-email: dev-nlcpy@sxarr.jp.nec.com
License: BSD
Download-URL: https://github.com/SX-Aurora/mpi4py-ve/releases/
Keywords: scientific computing,parallel computing,message passing interface,MPI
Platform: Linux
Platform: Unix
Classifier: Development Status :: 5 - Production/Stable
Classifier: License :: OSI Approved :: BSD License
Classifier: Operating System :: POSIX :: Linux
Classifier: Programming Language :: Python :: 3.6
Classifier: Programming Language :: Python :: 3.7
Classifier: Programming Language :: Python :: 3.8
Classifier: Programming Language :: C
Classifier: Programming Language :: Cython
Classifier: Programming Language :: Python :: 3 :: Only
Classifier: Topic :: Scientific/Engineering
Classifier: Topic :: Software Development
Provides: mpi4py_ve
